mebuex/__init__.py
mebuex/build_ext.py
mebuex/extension.py
mebuex/scripts/__init__.py
mebuex/scripts/gravelspoon.py
mebuex-1.3.0.dist-info/LICENSE
mebuex-1.3.0.dist-info/METADATA
mebuex-1.3.0.dist-info/WHEEL
mebuex-1.3.0.dist-info/entry_points.txt
mebuex-1.3.0.dist-info/top_level.txt
mebuex-1.3.0.dist-info/RECORD
