Metadata-Version: 2.1
Name: mebuex
Version: 1.3.0
Summary: Combining build_ext with the Meson build system
Author-email: "Malte J. Ziebarth" <mjz.science@fmvkb.de>
License: MIT
Project-URL: Homepage, https://github.com/mjziebarth/Mebuex
Project-URL: Bug Tracker, https://github.com/mjziebarth/Mebuex/issues
Classifier: Development Status :: 4 - Beta
Classifier: Programming Language :: Python :: 3
Classifier: License :: OSI Approved :: MIT License
Classifier: Framework :: Setuptools Plugin
Classifier: Intended Audience :: Developers
Classifier: Natural Language :: English
Classifier: Operating System :: POSIX :: Linux
Classifier: Topic :: Software Development :: Build Tools
License-File: LICENSE
Requires-Dist: meson
